hashai/__init__.py
hashai/assistant.py
hashai/memory.py
hashai/models.py
hashai/rag.py
hashai/api/__init__.py
hashai/api/api_generator.py
hashai/api/fastapi_app.py
hashai/cli/__init__.py
hashai/cli/main.py
hashai/knowledge_base/__init__.py
hashai/knowledge_base/document_loader.py
hashai/knowledge_base/retriever.py
hashai/knowledge_base/vector_store.py
hashai/llm/__init__.py
hashai/llm/anthropic.py
hashai/llm/base_llm.py
hashai/llm/deepseek.py
hashai/llm/gemini.py
hashai/llm/groq.py
hashai/llm/mistral.py
hashai/llm/openai.py
hashai/storage/__init__.py
hashai/storage/base_storage.py
hashai/storage/cloud_storage.py
hashai/storage/in_memory_storage.py
hashai/storage/local_storage.py
hashai/tools/__init__.py
hashai/tools/base_tool.py
hashai/tools/crypto.py
hashai/tools/duckduckgo.py
hashai/tools/stocks.py
hashai/tools/visual_verification.py
hashai/tools/web_browser.py
hashai/tools/web_browser_async.py
hashai/utils/__init__.py
hashai/utils/config.py
hashai/utils/date_utils.py
hashai/utils/file_utils.py
hashai/utils/logger.py
hashai/utils/validation_utils.py
tests/__init__.py
tests/test_assistant.py
tests/test_memory.py
tests/test_rag.py
hashai-0.3.19.dist-info/LICENSE
hashai-0.3.19.dist-info/METADATA
hashai-0.3.19.dist-info/WHEEL
hashai-0.3.19.dist-info/entry_points.txt
hashai-0.3.19.dist-info/top_level.txt
hashai-0.3.19.dist-info/RECORD
